certbot_dns_namesilo/__init__.py
certbot_dns_namesilo/_internal/__init__.py
certbot_dns_namesilo/_internal/dns_namesilo.py
certbot_dns_namesilo-0.1.1.dist-info/LICENSE.txt
certbot_dns_namesilo-0.1.1.dist-info/METADATA
certbot_dns_namesilo-0.1.1.dist-info/WHEEL
certbot_dns_namesilo-0.1.1.dist-info/entry_points.txt
certbot_dns_namesilo-0.1.1.dist-info/top_level.txt
certbot_dns_namesilo-0.1.1.dist-info/RECORD
